blackbox.v
module blackbox(a, l, b, n);
    output a;
    input  l, b, n;
    wire   w13, w23, w26, w28, w30, w31, w37, w40, w45, w47, w50, w54, w70, w78, w92;
    and a35(a, w31, w26);
    or  o16(w31, w70, w13);
    and a10(w70, w47, w45);
    and a21(w13, w47, w50);
    not n51(w50, w45);
    or  o86(w26, w30, w37);
    not n19(w30, w37);
    and a80(w37, n, w40);
    or  o67(w40, w54, b);
    not n17(w54, l);
    and a0(w45, l, w23);
    or  o60(w23, w78, w92);
    not n77(w78, b);
    not n85(w92, n);
    or  o99(w47, w28, l, n);
    not n61(w28, b);
endmodule // blackbox

blackbox_tb.v
module blackbox_test;
reg a,b,c;
wire s;

blackbox b1(s,a,b,c);
initial begin
$dumpfile("blackbox.vcd");
$dumpvars(0,blackbox_test);

c=0;a=0;b=0; # 10;
c=0;a=0;b=1; # 10;
c=0;a=1;b=0; # 10;
c=0;a=1;b=1; # 10;
c=1;a=0;b=0; # 10;
c=1;a=0;b=1; # 10;
c=1;a=1;b=0; # 10;
c=1;a=1;b=1; # 10;


$finish;

end
initial
    $monitor("At time %2t, s = %d a = %d b = %d c = %d",
                 $time, s, a, b, c);

endmodule // sc2_test

blackbox.vcd
$date
	Wed Aug 28 14:26:00 2019
$end
$version
	Icarus Verilog
$end
$timescale
	1s
$end
$scope module blackbox_test $end
$var wire 1 ! s $end
$var reg 1 " a $end
$var reg 1 # b $end
$var reg 1 $ c $end
$scope module b1 $end
$var wire 1 ! a $end
$var wire 1 # b $end
$var wire 1 " l $end
$var wire 1 $ n $end
$var wire 1 % w13 $end
$var wire 1 & w23 $end
$var wire 1 ' w26 $end
$var wire 1 ( w28 $end
$var wire 1 ) w30 $end
$var wire 1 * w31 $end
$var wire 1 + w37 $end
$var wire 1 , w40 $end
$var wire 1 - w45 $end
$var wire 1 . w47 $end
$var wire 1 / w50 $end
$var wire 1 0 w54 $end
$var wire 1 1 w70 $end
$var wire 1 2 w78 $end
$var wire 1 3 w92 $end
$upscope $end
$upscope $end
$enddefinitions $end
#0
$dumpvars
13
12
01
10
1/
1.
0-
1,
0+
1*
1)
1(
1'
1&
1%
0$
0#
0"
1!
$end
#10
0!
0*
0%
0.
02
0(
1#
#20
1!
1*
0/
0%
11
0,
12
1(
00
1-
1.
0#
1"
#30
1,
02
0(
1#
#40
1!
1%
1*
1/
01
0)
12
1(
10
0-
1+
03
0#
0"
1$
#50
0&
02
0(
1#
#60
0%
1!
0/
11
1)
1'
1-
0+
1&
0,
12
1(
00
0#
1"
#70
1!
1%
1*
1/
01
0)
0-
1+
0&
1,
02
0(
1#
